Workbook

Sheet Orginal
A1: Scenario | B1: Annual Grid Import | C1: Import Cost | D1: Annual Grid Export | E1: Export revenue | F1: Investment cost | G1: Net Expense | H1: Cost Difference from base scenario | I1: Cost Breakeven based on revenue | J1: Cost Break even based on difference | K1: Carbon Footprint (KgCO2eq) | L1: Carbon footprint Difference from Base scenario | M1: Battery Manufacturing CO2 (KG/KW capacity) | N1: PV Manufacturing CO2 (KG/KW capacity) | O1: Carbon Breakeven based on Difference from base scenario
A2: PV_NoBattery | B2: 14569.3 | C2: =B2*0.35 -> 5099.255 | D2: 18476.27 | E2: =D2*0.08 -> 1478.1016 | F2: 0 | G2: =C2-E2 -> 3621.1534 | H2: =3621.153-G2 -> -0.0004 | I2: =F2/E2 -> 0 | J2: =F2/H2 -> 0 | K2: 6875.788 | L2: =6875.79-K2 -> 0.002 | M2: 0 | N2: 13.64 | O2: 0
A3: 5kW | B3: 13145.04 | C3: =B3*0.35 -> 4600.764 | D3: 16925.51 | E3: =D3*0.08 -> 1354.0408 | F3: 5982.13 | G3: =C3-E3 -> 3246.7232 | H3: =3621.153-G3 -> 374.4298 | I3: =F3/E3 -> 4.4179836 | J3: =F3/H3 -> 15.97664 | K3: 6232.088 | L3: =6875.79-K3 -> 643.702 | M3: 546.6 | N3: 13.64 | O3: =((M3+N3)/L3) -> 0.87034062
A4: 8kW | B4: 12427.33 | C4: =B4*0.35 -> 4349.5655 | D4: 16142.26 | E4: =D4*0.08 -> 1291.3808 | F4: 8000.61 | G4: =C4-E4 -> 3058.1847 | H4: =3621.153-G4 -> 562.9683 | I4: =F4/E4 -> 6.1953918 | J4: =F4/H4 -> 14.211475 | K4: 5909.875 | L4: =6875.79-K4 -> 965.915 | M4: 874.56 | N4: 13.64 | O4: =((M4+N4)/L4) -> 0.91954261
A5: 12kW | B5: 11567.89 | C5: =B5*0.35 -> 4048.7615 | D5: 15204.36 | E5: =D5*0.08 -> 1216.3488 | F5: 10691.91 | G5: =C5-E5 -> 2832.4127 | H5: =3621.153-G5 -> 788.7403 | I5: =F5/E5 -> 8.7901678 | J5: =F5/H5 -> 13.555679 | K5: 5526.793 | L5: =6875.79-K5 -> 1348.997 | M5: 1311.84 | N5: 13.64 | O5: =((M5+N5)/L5) -> 0.98256705
A6: 15kW | B6: 11031.56 | C6: =B6*0.35 -> 3861.046 | D6: 14618.41 | E6: =D6*0.08 -> 1169.4728 | F6: 12710.39 | G6: =C6-E6 -> 2691.5732 | H6: =3621.153-G6 -> 929.5798 | I6: =F6/E6 -> 10.868479 | J6: =F6/H6 -> 13.673264 | K6: 5291.262 | L6: =6875.79-K6 -> 1584.528 | M6: 1639.8 | N6: 13.64 | O6: =((M6+N6)/L6) -> 1.0434906
A7: 20kW | B7: 10321.95 | C7: =B7*0.35 -> 3612.6825 | D7: 13841.47 | E7: =D7*0.08 -> 1107.3176 | F7: 16074.52 | G7: =C7-E7 -> 2505.3649 | H7: =3621.153-G7 -> 1115.7881 | I7: =F7/E7 -> 14.51663 | J7: =F7/H7 -> 14.406427 | K7: 4984.288 | L7: =6875.79-K7 -> 1891.502 | M7: 2186.4 | N7: 13.64 | O7: =((M7+N7)/L7) -> 1.163118
A8: 26kW | B8: 9714.28 | C8: =B8*0.35 -> 3399.998 | D8: 13174.98 | E8: =D8*0.08 -> 1053.9984 | F8: 20111.48 | G8: =C8-E8 -> 2345.9996 | H8: =3621.153-G8 -> 1275.1534 | I8: =F8/E8 -> 19.08113 | J8: =F8/H8 -> 15.771812 | K8: 4730.775 | L8: =6875.79-K8 -> 2145.015 | M8: 2842.32 | N8: 13.64 | O8: =((M8+N8)/L8) -> 1.3314406
A9: 50kW | B9: 8545.85 | C9: =B9*0.35 -> 2991.0475 | D9: 11874.43 | E9: =D9*0.08 -> 949.9544 | F9: 36259.3 | G9: =C9-E9 -> 2041.0931 | H9: =3621.153-G9 -> 1580.0599 | I9: =F9/E9 -> 38.169516 | J9: =F9/H9 -> 22.948054 | K9: 4311.241 | L9: =6875.79-K9 -> 2564.549 | M9: 5466 | N9: 13.64 | O9: =((M9+N9)/L9) -> 2.1366876

Sheet Additional PV
A1: Scenario | B1: Annual Grid Import | C1: Import Cost | D1: Annual Grid Export | E1: Export revenue | F1: Investment cost | G1: Net Expense | H1: Cost Difference from base scenario | I1: Cost Break even based on difference | J1: Cost Break even based on Revenue | K1: Carbon Footprint (KgCO2eq) | L1: Carbon Difference from Base scenario | M1: Battery Manufacturing CO2 (KG/KW capacity) | N1: PV Manufacturing CO2 (KG/KW capacity) | O1: Carbon Breakeven based on Difference from base scenario
A2: PV_NoBattery | B2: 14510.51 | C2: =B2*0.35 -> 5078.6785 | D2: 21465.37 | E2: =D2*0.08 -> 1717.2296 | F2: 1954.34 | G2: =C2-E2 -> 3361.4489 | H2: =3621.153-G2 -> 259.7041 | I2: =F2/H2 -> 7.5252566 | J2: =F2/E2 -> 1.1380773 | K2: 6850.442 | L2: =6875.78-K2 -> 25.338 | M2: 0 | N2: 15.45 | O2: =(('Load Shift'!M2+N2)/'Load Shift'!L2) -> 0.13973301
A3: 5kW | B3: 13067.79 | C3: =B3*0.35 -> 4573.7265 | D3: 19894.23 | E3: =D3*0.08 -> 1591.5384 | F3: 7943.02 | G3: =C3-E3 -> 2982.1881 | H3: =3621.153-G3 -> 638.9649 | I3: =F3/H3 -> 12.431074 | J3: =F3/E3 -> 4.9907812 | K3: 6198.171 | L3: =6875.78-K3 -> 677.609 | M3: 546.6 | N3: 15.45 | O3: =(('Load Shift'!M3+N3)/'Load Shift'!L3) -> 0.73887254
A4: 8kW | B4: 12326.66 | C4: =B4*0.35 -> 4314.331 | D4: 19085.95 | E4: =D4*0.08 -> 1526.876 | F4: 9965.42 | G4: =C4-E4 -> 2787.455 | H4: =3621.153-G4 -> 833.698 | I4: =F4/H4 -> 11.953273 | J4: =F4/E4 -> 6.5266728 | K4: 5865.449 | L4: =6875.78-K4 -> 1010.331 | M4: 874.56 | N4: 15.45 | O4: =(('Load Shift'!M4+N4)/'Load Shift'!L4) -> 0.82227813
A5: 12kW | B5: 11441.37 | C5: =B5*0.35 -> 4004.4795 | D5: 18119.79 | E5: =D5*0.08 -> 1449.5832 | F5: 12661.96 | G5: =C5-E5 -> 2554.8963 | H5: =3621.153-G5 -> 1066.2567 | I5: =F5/H5 -> 11.875152 | J5: =F5/E5 -> 8.734897 | K5: 5470.276 | L5: =6875.78-K5 -> 1405.504 | M5: 1311.84 | N5: 15.45 | O5: =(('Load Shift'!M5+N5)/'Load Shift'!L5) -> 0.90758037
A6: 15kW | B6: 10878.35 | C6: =B6*0.35 -> 3807.4225 | D6: 17504.63 | E6: =D6*0.08 -> 1400.3704 | F6: 14684.36 | G6: =C6-E6 -> 2407.0521 | H6: =3621.153-G6 -> 1214.1009 | I6: =F6/H6 -> 12.094843 | J6: =F6/E6 -> 10.486054 | K6: 5221.447 | L6: =6875.78-K6 -> 1654.333 | M6: 1639.8 | N6: 15.45 | O6: =(('Load Shift'!M6+N6)/'Load Shift'!L6) -> 0.97623823
A7: 20kW | B7: 10130.12 | C7: =B7*0.35 -> 3545.542 | D7: 16686.88 | E7: =D7*0.08 -> 1334.9504 | F7: 18055.04 | G7: =C7-E7 -> 2210.5916 | H7: =3621.153-G7 -> 1410.5614 | I7: =F7/H7 -> 12.799897 | J7: =F7/E7 -> 13.524877 | K7: 4896.28 | L7: =6875.78-K7 -> 1979.5 | M7: 2186.4 | N7: 15.45 | O7: =(('Load Shift'!M7+N7)/'Load Shift'!L7) -> 1.1028069
A8: 26kW | B8: 9478.2 | C8: =B8*0.35 -> 3317.37 | D8: 15972.96 | E8: =D8*0.08 -> 1277.8368 | F8: 22099.85 | G8: =C8-E8 -> 2039.5332 | H8: =3621.153-G8 -> 1581.6198 | I8: =F8/H8 -> 13.972922 | J8: =F8/E8 -> 17.294736 | K8: 4621.926 | L8: =6875.78-K8 -> 2253.854 | M8: 2842.32 | N8: 15.45 | O8: =(('Load Shift'!M8+N8)/'Load Shift'!L8) -> 1.2750274
A9: 50kW | B9: 8196.05 | C9: =B9*0.35 -> 2868.6175 | D9: 14556.53 | E9: =D9*0.08 -> 1164.5224 | F9: 38279.09 | G9: =C9-E9 -> 1704.0951 | H9: =3621.153-G9 -> 1917.0579 | I9: =F9/H9 -> 19.967623 | J9: =F9/E9 -> 32.871064 | K9: 4148.83 | L9: =6875.78-K9 -> 2726.95 | M9: 5466 | N9: 15.45 | O9: =(('Load Shift'!M9+N9)/'Load Shift'!L9) -> 2.0774541

Sheet Dynamic
A1: Scenario | B1: Annual Grid Import | C1: Import Cost | D1: Annual Grid Export | E1: Export revenue | F1: Investment cost | G1: Net Expense | H1: Cost Difference from base scenario | I1: Cost Breakeven based on revenue | J1: Cost Break even based on difference | K1: Carbon Footprint (KgCO2eq) | L1: Carbon Difference from Base scenario | M1: Battery Manufacturing CO2 (KG/KW capacity) | N1: PV Manufacturing CO2 (KG/KW capacity) | O1: Carbon Breakeven based on Difference from base scenario
A2: PV_NoBattery | B2: 15134.16 | C2: 2785.9289 | D2: 19041.13 | E2: =D2*0.08 -> 1523.2904 | F2: 0 | G2: =C2-E2 -> 1262.6385 | H2: =3621.153-G2 -> 2358.5145 | I2: =F2/E2 -> 0 | J2: =F2/H2 -> 0 | K2: 7141.838 | L2: =6875.78-K2 -> -266.058 | M2: 0 | N2: 13.64 | O2: =(('Load Shift'!M2+N2)/'Load Shift'!L2) -> 0.123363
A3: 5kW | B3: 14176.42 | C3: 2447.0803 | D3: 17888.51 | E3: =D3*0.08 -> 1431.0808 | F3: 5982.13 | G3: =C3-E3 -> 1015.9995 | H3: =3621.153-G3 -> 2605.1535 | I3: =F3/E3 -> 4.1801483 | J3: =F3/H3 -> 2.2962678 | K3: 6717.993 | L3: =6875.78-K3 -> 157.787 | M3: 546.6 | N3: 13.64 | O3: =(('Load Shift'!M3+N3)/'Load Shift'!L3) -> 0.73649311
A4: 8kW | B4: 13709.11 | C4: 2285.0735 | D4: 17325.31 | E4: =D4*0.08 -> 1386.0248 | F4: 8000.61 | G4: =C4-E4 -> 899.0487 | H4: =3621.153-G4 -> 2722.1043 | I4: =F4/E4 -> 5.7723426 | J4: =F4/H4 -> 2.9391269 | K4: 6514.238 | L4: =6875.78-K4 -> 361.542 | M4: 874.56 | N4: 13.64 | O4: =(('Load Shift'!M4+N4)/'Load Shift'!L4) -> 0.82060587
A5: 12kW | B5: 13160.11 | C5: 2100.319 | D5: 16661.46 | E5: =D5*0.08 -> 1332.9168 | F5: 10691.91 | G5: =C5-E5 -> 767.40216 | H5: =3621.153-G5 -> 2853.7508 | I5: =F5/E5 -> 8.0214384 | J5: =F5/H5 -> 3.7466165 | K5: 6277.46 | L5: =6875.78-K5 -> 598.32 | M5: 1311.84 | N5: 13.64 | O5: =(('Load Shift'!M5+N5)/'Load Shift'!L5) -> 0.90634272
A6: 15kW | B6: 12826.41 | C6: 1984.7878 | D6: 16252.15 | E6: =D6*0.08 -> 1300.172 | F6: 12710.39 | G6: =C6-E6 -> 684.61579 | H6: =3621.153-G6 -> 2936.5372 | I6: =F6/E6 -> 9.7759296 | J6: =F6/H6 -> 4.3283599 | K6: 6136.636 | L6: =6875.78-K6 -> 739.144 | M6: 1639.8 | N6: 13.64 | O6: =(('Load Shift'!M6+N6)/'Load Shift'!L6) -> 0.97517073
A7: 20kW | B7: 12400.98 | C7: 1828.2271 | D7: 15717.98 | E7: =D7*0.08 -> 1257.4384 | F7: 16074.52 | G7: =C7-E7 -> 570.78873 | H7: =3621.153-G7 -> 3050.3643 | I7: =F7/E7 -> 12.783545 | J7: =F7/H7 -> 5.269705 | K7: 5963.51 | L7: =6875.78-K7 -> 912.27 | M7: 2186.4 | N7: 13.64 | O7: =(('Load Shift'!M7+N7)/'Load Shift'!L7) -> 1.1019004
A8: 26kW | B8: 12117.4 | C8: 1694.2823 | D8: 15328.01 | E8: =D8*0.08 -> 1226.2408 | F8: 20111.48 | G8: =C8-E8 -> 468.04152 | H8: =3621.153-G8 -> 3153.1115 | I8: =F8/E8 -> 16.400922 | J8: =F8/H8 -> 6.3782965 | K8: 5862.643 | L8: =6875.78-K8 -> 1013.137 | M8: 2842.32 | N8: 13.64 | O8: =(('Load Shift'!M8+N8)/'Load Shift'!L8) -> 1.2742199
A9: 50kW | B9: 12085.66 | C9: 1433.9471 | D9: 14997.04 | E9: =D9*0.08 -> 1199.7632 | F9: 36259.3 | G9: =C9-E9 -> 234.18393 | H9: =3621.153-G9 -> 3386.9691 | I9: =F9/E9 -> 30.222047 | J9: =F9/H9 -> 10.70553 | K9: 5978.491 | L9: =6875.78-K9 -> 897.289 | M9: 5466 | N9: 13.64 | O9: =(('Load Shift'!M9+N9)/'Load Shift'!L9) -> 2.0767682

Sheet Load Shift
A1: Scenario | B1: Annual Grid Import | C1: Import Cost | D1: Annual Grid Export | E1: Export revenue | F1: Investment cost | G1: Net Expense | H1: Cost Difference from base scenario | I1: Cost Breakeven based on revenue | J1: Cost Break even based on difference | K1: Carbon Footprint (KgCO2eq) | L1: Carbon Difference from Base scenario | M1: Battery Manufacturing CO2 (KG/KW capacity) | N1: PV Manufacturing CO2 (KG/KW capacity) | O1: Carbon Breakeven based on Difference from base scenario
A2: PV_NoBattery | B2: 14393.24 | C2: =B2*0.35 -> 5037.634 | D2: 18300.04 | E2: =D2*0.08 -> 1464.0032 | F2: 0 | G2: =C2-E2 -> 3573.6308 | H2: =3621.153-G2 -> 47.5222 | I2: =F2/E2 -> 0 | J2: =F2/H2 -> 0 | K2: 6765.212 | L2: =6875.78-K2 -> 110.568 | M2: 0 | N2: 13.64 | O2: =(('Load Shift'!M2+N2)/'Load Shift'!L2) -> 0.123363
A3: 5kW | B3: 12955.65 | C3: =B3*0.35 -> 4534.4775 | D3: 16735.68 | E3: =D3*0.08 -> 1338.8544 | F3: 5982.13 | G3: =C3-E3 -> 3195.6231 | H3: =3621.153-G3 -> 425.5299 | I3: =F3/E3 -> 4.468096 | J3: =F3/H3 -> 14.058072 | K3: 6115.094 | L3: =6875.78-K3 -> 760.686 | M3: 546.6 | N3: 13.64 | O3: =(('Load Shift'!M3+N3)/'Load Shift'!L3) -> 0.73649311
A4: 8kW | B4: 12234.4 | C4: =B4*0.35 -> 4282.04 | D4: 15949.62 | E4: =D4*0.08 -> 1275.9696 | F4: 8000.61 | G4: =C4-E4 -> 3006.0704 | H4: =3621.153-G4 -> 615.0826 | I4: =F4/E4 -> 6.2702199 | J4: =F4/H4 -> 13.007375 | K4: 5793.409 | L4: =6875.78-K4 -> 1082.371 | M4: 874.56 | N4: 13.64 | O4: =(('Load Shift'!M4+N4)/'Load Shift'!L4) -> 0.82060587
A5: 12kW | B5: 11374.55 | C5: =B5*0.35 -> 3981.0925 | D5: 15011.49 | E5: =D5*0.08 -> 1200.9192 | F5: 10691.91 | G5: =C5-E5 -> 2780.1733 | H5: =3621.153-G5 -> 840.9797 | I5: =F5/E5 -> 8.9031052 | J5: =F5/H5 -> 12.713636 | K5: 5413.331 | L5: =6875.78-K5 -> 1462.449 | M5: 1311.84 | N5: 13.64 | O5: =(('Load Shift'!M5+N5)/'Load Shift'!L5) -> 0.90634272
A6: 15kW | B6: 10841.77 | C6: =B6*0.35 -> 3794.6195 | D6: 14429.49 | E6: =D6*0.08 -> 1154.3592 | F6: 12710.39 | G6: =C6-E6 -> 2640.2603 | H6: =3621.153-G6 -> 980.8927 | I6: =F6/E6 -> 11.010776 | J6: =F6/H6 -> 12.957982 | K6: 5180.241 | L6: =6875.78-K6 -> 1695.539 | M6: 1639.8 | N6: 13.64 | O6: =(('Load Shift'!M6+N6)/'Load Shift'!L6) -> 0.97517073
A7: 20kW | B7: 10141.18 | C7: =B7*0.35 -> 3549.413 | D7: 13663.05 | E7: =D7*0.08 -> 1093.044 | F7: 16074.52 | G7: =C7-E7 -> 2456.369 | H7: =3621.153-G7 -> 1164.784 | I7: =F7/E7 -> 14.706197 | J7: =F7/H7 -> 13.80043 | K7: 4879.193 | L7: =6875.78-K7 -> 1996.587 | M7: 2186.4 | N7: 13.64 | O7: =(('Load Shift'!M7+N7)/'Load Shift'!L7) -> 1.1019004
A8: 26kW | B8: 9544.71 | C8: =B8*0.35 -> 3340.6485 | D8: 13008.91 | E8: =D8*0.08 -> 1040.7128 | F8: 20111.48 | G8: =C8-E8 -> 2299.9357 | H8: =3621.153-G8 -> 1321.2173 | I8: =F8/E8 -> 19.324717 | J8: =F8/H8 -> 15.221932 | K8: 4634.44 | L8: =6875.78-K8 -> 2241.34 | M8: 2842.32 | N8: 13.64 | O8: =(('Load Shift'!M8+N8)/'Load Shift'!L8) -> 1.2742199
A9: 50kW | B9: 8412.84 | C9: =B9*0.35 -> 2944.494 | D9: 11756.1 | E9: =D9*0.08 -> 940.488 | F9: 36259.3 | G9: =C9-E9 -> 2004.006 | H9: =3621.153-G9 -> 1617.147 | I9: =F9/E9 -> 38.553708 | J9: =F9/H9 -> 22.421771 | K9: 4237.238 | L9: =6875.78-K9 -> 2638.542 | M9: 5466 | N9: 13.64 | O9: =(('Load Shift'!M9+N9)/'Load Shift'!L9) -> 2.0767682
